COPYRIGHT
LICENSE
MANIFEST.in
README.rst
setup.py
version
fhir_server/__init__.py
fhir_server/config.py
fhir_server/fhir_uwsgi.py
fhir_server/gnuhealth_fhir_server.py
fhir_server/server_uwsgi.ini
fhir_server/common/__init__.py
fhir_server/common/extensions.py
fhir_server/common/utils.py
fhir_server/fhir/__init__.py
fhir_server/fhir/adverse_reaction.py
fhir_server/fhir/alert.py
fhir_server/fhir/allergy_intolerance.py
fhir_server/fhir/atom.py
fhir_server/fhir/base_classes.py
fhir_server/fhir/binary.py
fhir_server/fhir/care_plan.py
fhir_server/fhir/composition.py
fhir_server/fhir/concept_map.py
fhir_server/fhir/condition.py
fhir_server/fhir/config.py
fhir_server/fhir/conformance.py
fhir_server/fhir/data_types.py
fhir_server/fhir/device.py
fhir_server/fhir/device_observation_report.py
fhir_server/fhir/diagnostic_order.py
fhir_server/fhir/diagnostic_report.py
fhir_server/fhir/document_manifest.py
fhir_server/fhir/document_reference.py
fhir_server/fhir/encounter.py
fhir_server/fhir/family_history.py
fhir_server/fhir/group.py
fhir_server/fhir/html.py
fhir_server/fhir/imaging_study.py
fhir_server/fhir/immunization.py
fhir_server/fhir/immunization_recommendation.py
fhir_server/fhir/list_.py
fhir_server/fhir/location.py
fhir_server/fhir/media.py
fhir_server/fhir/medication.py
fhir_server/fhir/medication_administration.py
fhir_server/fhir/medication_dispense.py
fhir_server/fhir/medication_prescription.py
fhir_server/fhir/medication_statement.py
fhir_server/fhir/message_header.py
fhir_server/fhir/misc.py
fhir_server/fhir/narrative.py
fhir_server/fhir/observation.py
fhir_server/fhir/operation_outcome.py
fhir_server/fhir/order.py
fhir_server/fhir/order_response.py
fhir_server/fhir/organization.py
fhir_server/fhir/other.py
fhir_server/fhir/patient.py
fhir_server/fhir/practitioner.py
fhir_server/fhir/primitive_types.py
fhir_server/fhir/procedure.py
fhir_server/fhir/profile.py
fhir_server/fhir/provenance.py
fhir_server/fhir/query.py
fhir_server/fhir/questionnaire.py
gnuhealth_fhir_server.egg-info/PKG-INFO
gnuhealth_fhir_server.egg-info/SOURCES.txt
gnuhealth_fhir_server.egg-info/dependency_links.txt
gnuhealth_fhir_server.egg-info/not-zip-safe
gnuhealth_fhir_server.egg-info/requires.txt
gnuhealth_fhir_server.egg-info/top_level.txt