Metadata-Version: 2.1
Name: gnuhealth-fhir-server
Version: 0.9b7
Summary: The GNU Health FHIR Server
Home-page: https://www.gnuhealth.org
Download-URL: http://ftp.gnu.org/gnu/health
Author: GNU Solidario
Author-email: info@gnuhealth.org
Keywords: health API REST HL7 FHIR
Platform: any
Classifier: Development Status :: 4 - Beta
Classifier: Environment :: Web Environment
Classifier: Framework :: Flask
Classifier: Intended Audience :: Science/Research
Classifier: Intended Audience :: Healthcare Industry
Classifier: License :: OSI Approved :: GNU General Public License v3 or later (GPLv3+)
Classifier: Natural Language :: English
Classifier: Operating System :: OS Independent
Classifier: Programming Language :: Python :: 3
Classifier: Topic :: Scientific/Engineering :: Bio-Informatics
Classifier: Topic :: Scientific/Engineering :: Medical Science Apps.
License-File: LICENSE
